{
  "version": "7",
  "dialect": "postgresql",
  "entries": [
    {
      "idx": 0,
      "version": "7",
      "when": 1756675900582,
      "tag": "0000_glossy_krista_starr",
      "breakpoints": true
    },
    {
      "idx": 1,
      "version": "7",
      "when": 1756761462644,
      "tag": "0001_free_omega_red",
      "breakpoints": true
    },
    {
      "idx": 2,
      "version": "7",
      "when": 1756765317618,
      "tag": "0002_refactor_riders_safe",
      "breakpoints": true
    }
  ]
}